ldmudefuns/__init__.py
ldmudefuns/help.py
ldmudefuns/reload.py
ldmudefuns/startup.py
ldmud_efuns-0.2.2.dist-info/LICENSE
ldmud_efuns-0.2.2.dist-info/METADATA
ldmud_efuns-0.2.2.dist-info/WHEEL
ldmud_efuns-0.2.2.dist-info/entry_points.txt
ldmud_efuns-0.2.2.dist-info/top_level.txt
ldmud_efuns-0.2.2.dist-info/RECORD
