Metadata-Version: 2.1
Name: ldmud-efuns
Version: 0.2.2
Summary: Python Efun management package for LDMud
Home-page: https://github.com/ldmud/python-efuns
Author: LDMud Team
Author-email: ldmud-dev@UNItopia.DE
License: UNKNOWN
Platform: UNKNOWN
Classifier: Programming Language :: Python :: 3
Classifier: License :: OSI Approved :: ISC License (ISCL)
Classifier: Operating System :: OS Independent
